filedb/__init__.py
filedb/cache.py
filedb/db.py
filedb/hash.py
filedb/index.py
filedb/key.py
filedb/lock.py
filedb/multiprocessing.py
filedb/psutil.py
filedb/query.py
filedb/storage.py
pyfiledb-0.3.dist-info/LICENSE
pyfiledb-0.3.dist-info/METADATA
pyfiledb-0.3.dist-info/WHEEL
pyfiledb-0.3.dist-info/top_level.txt
pyfiledb-0.3.dist-info/RECORD
