Metadata-Version: 2.1
Name: pyfiledb
Version: 0.3
Summary: File database
Home-page: https://github.com/psarka/filedb
Author: Paulius Šarka
Author-email: paulius.sarka@gmail.com
License: UNKNOWN
Platform: UNKNOWN
Classifier: Programming Language :: Python :: 3
Classifier: License :: OSI Approved :: MIT License
Classifier: Operating System :: OS Independent
Requires-Python: >=3.6
Requires-Dist: atomicwrites
Requires-Dist: crcmod
Requires-Dist: fasteners
Requires-Dist: google-cloud-storage
Requires-Dist: pymongo
Requires-Dist: psutil ; sys_platform != "linux"
